{
  "profile": "zh",
  "version": "0.1",
  "roles": {
    "agent.entry_rules": "AGENTS.md",
    "system.context.project_status": "_系统/上下文/当前项目.md",
    "system.context.decisions": "_系统/上下文/决策.md",
    "system.tasks.current_work": "_系统/任务/当前工作.md",
    "identity.local": "_系统/身份/",
    "lessons.local": "_系统/教训/",
    "handoff.local": ".starwork/handoff/",
    "work.starter.references": "参考资料/",
    "work.starter.outputs_drafts": "输出/草稿/",
    "work.starter.outputs_final": "输出/确认成果/",
    "work.matters.registry": "事项/注册表.md"
  },
  "legacyAliases": {
    "system.context.project_status": [
      "_系统/上下文/项目状态.md"
    ]
  }
}
